[{"createdAt":"2025-03-19T11:46:09.710Z","updatedAt":"2025-03-19T12:18:13.000Z","id":"TlBUn724Mr6lnF5M","name":"GitHub Backup","active":true,"nodes":[{"parameters":{"filters":{},"requestOptions":{}},"type":"n8n-nodes-base.n8n","typeVersion":1,"position":[220,0],"id":"e25f37ec-e981-4008-992f-a26121215cd0","name":"n8n","credentials":{"n8nApi":{"id":"MNX154G2w5YdMZFv","name":"n8n account"}}},{"parameters":{"resource":"file","operation":"edit","owner":{"__rl":true,"value":"Molizanee","mode":"list","cachedResultName":"Molizanee","cachedResultUrl":"https://github.com/Molizanee"},"repository":{"__rl":true,"value":"n8n-workflows","mode":"list","cachedResultName":"n8n-workflows","cachedResultUrl":"https://github.com/Molizanee/n8n-workflows"},"filePath":"backups/workflows.json","binaryData":true,"commitMessage":"={{ $now }}","additionalParameters":{"author":{"name":"David Molizane","email":"dmolizane@gmail.com"}}},"type":"n8n-nodes-base.github","typeVersion":1,"position":[660,0],"id":"ad3761b4-a305-4e2c-af4b-4cf900297f32","name":"GitHub","retryOnFail":true,"credentials":{"githubApi":{"id":"2ZmqmOaWOwZ2Kr0f","name":"GitHub account"}}},{"parameters":{"operation":"toJson","options":{"fileName":"={{ $now }}"}},"type":"n8n-nodes-base.convertToFile","typeVersion":1.1,"position":[440,0],"id":"2793c41e-288e-4d10-9620-4a170ee7c9cb","name":"Convert to File"},{"parameters":{"rule":{"interval":[{"triggerAtHour":5}]}},"type":"n8n-nodes-base.scheduleTrigger","typeVersion":1.2,"position":[20,0],"id":"2ee75308-4103-48db-9752-7cb4fa365557","name":"Schedule Trigger"}],"connections":{"n8n":{"main":[[{"node":"Convert to File","type":"main","index":0}]]},"Convert to File":{"main":[[{"node":"GitHub","type":"main","index":0}]]},"Schedule Trigger":{"main":[[{"node":"n8n","type":"main","index":0}]]}},"settings":{"executionOrder":"v1","timezone":"America/Sao_Paulo","callerPolicy":"workflowsFromSameOwner"},"staticData":{"node:Schedule Trigger":{"recurrenceRules":[]}},"meta":{"templateCredsSetupCompleted":true},"pinData":{},"versionId":"750bdd3c-8a85-485c-9b6d-15009a6d83e6","triggerCount":1,"tags":[]},{"createdAt":"2025-02-28T13:46:08.913Z","updatedAt":"2025-03-16T23:35:02.000Z","id":"dlXJlUPMeZ4ck0NI","name":"Notion","active":true,"nodes":[{"parameters":{"rule":{"interval":[{"triggerAtHour":7}]}},"type":"n8n-nodes-base.scheduleTrigger","typeVersion":1.2,"position":[200,-120],"id":"85976e3e-7fe7-4f24-b271-1a9b4a3e1778","name":"Schedule Trigger"},{"parameters":{"jsCode":"function formatDate() {\n  const date = new Date()\n  const months = ['January', 'February', 'March', 'April', 'May','June','July', 'August', 'September','October','November', 'December'];\n\n  const pageTitle = `${date.getDate()} ${months[date.getMonth()]} of ${date.getFullYear()}`\n\n  const notionDate = `${months[date.getMonth()]} ${date.getDate()}, ${date.getFullYear()}`\n\n  \n  return {pageTitle, notionDate}\n}\n\nconst today = formatDate()\n\nreturn today\n"},"type":"n8n-nodes-base.code","typeVersion":2,"position":[420,-120],"id":"b445d14d-2a10-49fe-a6a3-a74936481c8b","name":"Get Today"},{"parameters":{"content":"# Page Titles Updates","height":520,"width":1900,"color":5},"type":"n8n-nodes-base.stickyNote","typeVersion":1,"position":[80,-280],"id":"2019f843-ab56-4860-b2cc-1e81c402dd05","name":"Sticky Note"},{"parameters":{"jsCode":"const databases = [\n  {\n    dbUrl: \"https://www.notion.so/1a064eabfee8804499d4ca81957ae406?v=1a064eabfee880fd9cc1000c07f6431c&pvs=4\",\n    toFilter: \"Date\",\n    filter: $input.first().json.notionDate,\n    pageUpdatedTitle: `Day Register: ${$input.first().json.pageTitle}`\n  },\n]\n\nreturn databases"},"type":"n8n-nodes-base.code","typeVersion":2,"position":[640,-120],"id":"0e6911c9-b16e-4ebd-9349-ae99d2224746","name":"Databases do update"},{"parameters":{"options":{}},"type":"n8n-nodes-base.splitInBatches","typeVersion":3,"position":[860,-120],"id":"4bc707d8-e436-4f78-8190-f910a476b94c","name":"Loop Over Items"},{"parameters":{"resource":"databasePage","operation":"getAll","databaseId":{"__rl":true,"value":"={{ $('Loop Over Items').item.json.dbUrl }}","mode":"url"},"filterType":"manual","filters":{"conditions":[{"key":"Date|date","condition":"equals","date":"={{ $json.filter }}"}]},"options":{}},"type":"n8n-nodes-base.notion","typeVersion":2.2,"position":[1300,-20],"id":"6a4ffa47-b641-40a2-85e2-0b8d8aad559f","name":"Get Pages","credentials":{"notionApi":{"id":"EWb3bodjrNNLbaml","name":"Notion account"}}},{"parameters":{"resource":"databasePage","operation":"update","pageId":{"__rl":true,"value":"={{ $json.id }}","mode":"id"},"propertiesUi":{"propertyValues":[{"key":"Name|title","title":"={{ $('Loop Over Items').item.json.pageUpdatedTitle }}"}]},"options":{}},"type":"n8n-nodes-base.notion","typeVersion":2.2,"position":[1520,-20],"id":"aeee46c2-5b2b-4f3e-bcb7-314b56fe82d8","name":"Update Pages","credentials":{"notionApi":{"id":"EWb3bodjrNNLbaml","name":"Notion account"}}},{"parameters":{"chatId":"6753173397","text":"=Automations for Notion succeeded✅","additionalFields":{"appendAttribution":false}},"type":"n8n-nodes-base.telegram","typeVersion":1.2,"position":[1320,-220],"id":"484f7b48-62b6-44d5-b9a0-c175238014d7","name":"Telegram","webhookId":"89d67465-8ef3-4c49-b308-630dd4b745f7","credentials":{"telegramApi":{"id":"VKHv9q5tVerjzJVq","name":"MolizaneBot"}}},{"parameters":{"chatId":"6753173397","text":"=Page {{ $json.name }}, updated successful✅","additionalFields":{}},"type":"n8n-nodes-base.telegram","typeVersion":1.2,"position":[1740,-20],"id":"914591f2-81c3-4b8d-9da6-7aec43c6b5b3","name":"Send Confirmation","webhookId":"df16e688-4341-4112-a967-189793cd3722","credentials":{"telegramApi":{"id":"VKHv9q5tVerjzJVq","name":"MolizaneBot"}}},{"parameters":{"aggregate":"aggregateAllItemData","options":{}},"type":"n8n-nodes-base.aggregate","typeVersion":1,"position":[1120,-220],"id":"a252df1a-12a3-46f3-889b-b6acdb921b4a","name":"Aggregate"}],"connections":{"Schedule Trigger":{"main":[[{"node":"Get Today","type":"main","index":0}]]},"Get Today":{"main":[[{"node":"Databases do update","type":"main","index":0}]]},"Databases do update":{"main":[[{"node":"Loop Over Items","type":"main","index":0}]]},"Loop Over Items":{"main":[[{"node":"Aggregate","type":"main","index":0}],[{"node":"Get Pages","type":"main","index":0}]]},"Get Pages":{"main":[[{"node":"Update Pages","type":"main","index":0}]]},"Update Pages":{"main":[[{"node":"Send Confirmation","type":"main","index":0}]]},"Send Confirmation":{"main":[[{"node":"Loop Over Items","type":"main","index":0}]]},"Aggregate":{"main":[[{"node":"Telegram","type":"main","index":0}]]}},"settings":{"executionOrder":"v1","timezone":"America/Sao_Paulo","callerPolicy":"workflowsFromSameOwner"},"staticData":{"node:Schedule Trigger":{"recurrenceRules":[]}},"meta":{"templateCredsSetupCompleted":true},"pinData":{},"versionId":"d049dba2-8918-471e-8e03-a00c899d321d","triggerCount":1,"tags":[]}]